{"AllowArmCoping":false,"AllowCenterBolts":false,"AllowA354BCBolts":false,"PoleStructure":{"PoleDiameterIn":21.0,"WallThickness":0.0,"PoleTaper":0.25,"PlateFinish":0},"ThruPlateConnection":{"ThruPlateOpening":15.0,"ConnectionType":1,"BracketWidth":15.125,"Height":18.0,"ConnectionTypeLabel":"Thru Plate","PlateFinish":1,"Id":"f1912ef5-6afb-4864-a3db-77d4677d1f37","Label":"","Thickness":0.625},"TubularDavitArm":{"Armtype":1,"Rise":6.875,"Bent":false,"Radius":0.0,"Dft":0.0,"AttachLabel":"","Azimuth":0.0,"DavitPropertyLabel":"","ArmJoints":[{"Id":"7ea1fca3-e919-410f-9165-0ba629bd4050","JointLabel":"Test #2","HorizontalOffset":0.0,"VerticalOffset":0.0,"Diameter":13.75,"UserDefined":true}],"ArmResults":{"Common":[{"Id":"6929f6ac-6479-4f9a-983e-68e2bdb8a9f7","LoadCase":"","Label":"","RelDist":0.0,"JointLabel":"","LongitudinalOffset":0.0,"TransverseOffset":0.0,"VerticalOffset":0.0,"AxialForce":1.5,"VerticalShear":1.0,"HorizontalShear":10.5,"HorizontalMoment":143.0,"VerticalMoment":16.125,"Torsion":5.9}]},"DesignMethodSpecified":1,"DesignMethodUsed":0,"NonUserArmJoints":[],"PoleDiameterIn":0.0,"UseArmPoleOffsets":false,"Label":"","MaterialSpecification":0,"TipFlatWidthInches":0.0,"BaseFlatWidthInches":13.75,"MaterialThicknessInches":0.1875,"Shape":{"Id":null,"SideCount":8,"TubeOrientation":0,"Description":"Octagonal","IsTubing":false,"IsRegularPolygon":false},"Finish":0,"LengthFt":13.75,"TipVerticalOffset":0.0,"TipHorizontalOffset":0.0},"SaddleBracket":{"BlackWeight":0.0,"BoltThreadsInShearPlane":false,"BoltTopEdgeDistance":1.5,"IsStandardBracket":false,"BoltWeight":9.738,"BracketSideWidth":5.125,"BracketWeight":99.4492,"GalvWeight":0.0,"MaximumBoltOffset":1.5,"StandardBracketMinEdgeDist":0.0,"BracketAnalysisLoads":{"DesignWorked":true,"BracketAnalysisResults":{"BracketLegStress":{"Loadcase":"Common","JointLabel":null,"LoadID":"6929f6ac-6479-4f9a-983e-68e2bdb8a9f7","ControllingBracketLoad":{"LoadsAtPoleFace":{"Id":"6929f6ac-6479-4f9a-983e-68e2bdb8a9f7","LoadCase":"","Label":"","RelDist":0.0,"JointLabel":"","LongitudinalOffset":0.0,"TransverseOffset":0.0,"VerticalOffset":0.0,"AxialForce":1.5,"VerticalShear":1.0,"HorizontalShear":10.5,"HorizontalMoment":143.0,"VerticalMoment":16.125,"Torsion":5.9},"ControllingStressTypeResults":{"BracketLegStress":true,"BracketShearRupture":true,"BracketBearing":true,"BracketBolts":true},"GoverningElement":"Bolt &  Bracket","Id":"6929f6ac-6479-4f9a-983e-68e2bdb8a9f7","LoadCase":"","Label":"","RelDist":0.0,"JointLabel":"","LongitudinalOffset":0.0,"TransverseOffset":0.0,"VerticalOffset":0.0,"AxialForce":1.5,"VerticalShear":1.0,"HorizontalShear":10.5,"HorizontalMoment":140.375,"VerticalMoment":15.75,"Torsion":5.9},"Description":"Bracket Leg Stress","Value":28.16017264095991,"Allowable":65.0,"Ratio":"43.32%","InteractionRatio":0.4332334252455371,"ResultsMsg":"Bracket Leg Stress works: 43.32%","IsOverstressed":false},"BracketShearRupture":{"Loadcase":"Common","JointLabel":null,"LoadID":"6929f6ac-6479-4f9a-983e-68e2bdb8a9f7","ControllingBracketLoad":{"LoadsAtPoleFace":{"Id":"6929f6ac-6479-4f9a-983e-68e2bdb8a9f7","LoadCase":"","Label":"","RelDist":0.0,"JointLabel":"","LongitudinalOffset":0.0,"TransverseOffset":0.0,"VerticalOffset":0.0,"AxialForce":1.5,"VerticalShear":1.0,"HorizontalShear":10.5,"HorizontalMoment":143.0,"VerticalMoment":16.125,"Torsion":5.9},"ControllingStressTypeResults":{"BracketLegStress":true,"BracketShearRupture":true,"BracketBearing":true,"BracketBolts":true},"GoverningElement":"Bolt &  Bracket","Id":"6929f6ac-6479-4f9a-983e-68e2bdb8a9f7","LoadCase":"","Label":"","RelDist":0.0,"JointLabel":"","LongitudinalOffset":0.0,"TransverseOffset":0.0,"VerticalOffset":0.0,"AxialForce":1.5,"VerticalShear":1.0,"HorizontalShear":10.5,"HorizontalMoment":140.375,"VerticalMoment":15.75,"Torsion":5.9},"Description":"Bracket Shear Rupture","Value":28.041232610037987,"Allowable":36.0,"Ratio":"77.89%","InteractionRatio":0.77892312805661079,"ResultsMsg":"Bracket Shear Rupture works: 77.89%","IsOverstressed":false},"BracketBearing":{"Loadcase":"Common","JointLabel":null,"LoadID":"6929f6ac-6479-4f9a-983e-68e2bdb8a9f7","ControllingBracketLoad":{"LoadsAtPoleFace":{"Id":"6929f6ac-6479-4f9a-983e-68e2bdb8a9f7","LoadCase":"","Label":"","RelDist":0.0,"JointLabel":"","LongitudinalOffset":0.0,"TransverseOffset":0.0,"VerticalOffset":0.0,"AxialForce":1.5,"VerticalShear":1.0,"HorizontalShear":10.5,"HorizontalMoment":143.0,"VerticalMoment":16.125,"Torsion":5.9},"ControllingStressTypeResults":{"BracketLegStress":true,"BracketShearRupture":true,"BracketBearing":true,"BracketBolts":true},"GoverningElement":"Bolt &  Bracket","Id":"6929f6ac-6479-4f9a-983e-68e2bdb8a9f7","LoadCase":"","Label":"","RelDist":0.0,"JointLabel":"","LongitudinalOffset":0.0,"TransverseOffset":0.0,"VerticalOffset":0.0,"AxialForce":1.5,"VerticalShear":1.0,"HorizontalShear":10.5,"HorizontalMoment":140.375,"VerticalMoment":15.75,"Torsion":5.9},"Description":"Bracket Bearing Stress","Value":52.577311143821227,"Allowable":152.0,"Ratio":"34.59%","InteractionRatio":0.34590336278829753,"ResultsMsg":"Bracket Bearing Stress works: 34.59%","IsOverstressed":false},"BracketBolts":{"Loadcase":"Common","JointLabel":null,"LoadID":"6929f6ac-6479-4f9a-983e-68e2bdb8a9f7","ControllingBracketLoad":{"LoadsAtPoleFace":{"Id":"6929f6ac-6479-4f9a-983e-68e2bdb8a9f7","LoadCase":"","Label":"","RelDist":0.0,"JointLabel":"","LongitudinalOffset":0.0,"TransverseOffset":0.0,"VerticalOffset":0.0,"AxialForce":1.5,"VerticalShear":1.0,"HorizontalShear":10.5,"HorizontalMoment":143.0,"VerticalMoment":16.125,"Torsion":5.9},"ControllingStressTypeResults":{"BracketLegStress":true,"BracketShearRupture":true,"BracketBearing":true,"BracketBolts":true},"GoverningElement":"Bolt &  Bracket","Id":"6929f6ac-6479-4f9a-983e-68e2bdb8a9f7","LoadCase":"","Label":"","RelDist":0.0,"JointLabel":"","LongitudinalOffset":0.0,"TransverseOffset":0.0,"VerticalOffset":0.0,"AxialForce":1.5,"VerticalShear":1.0,"HorizontalShear":10.5,"HorizontalMoment":140.375,"VerticalMoment":15.75,"Torsion":5.9},"Description":"Bracket Bolt Shear Stress","Value":41.860916515781227,"Allowable":54.0,"Ratio":"77.52%","InteractionRatio":0.77520215769965239,"ResultsMsg":"Bracket Bolt Shear Stress works: 77.52%","IsOverstressed":false}},"ControllingLoadcaseList":[{"LoadsAtPoleFace":{"Id":"6929f6ac-6479-4f9a-983e-68e2bdb8a9f7","LoadCase":"","Label":"","RelDist":0.0,"JointLabel":"","LongitudinalOffset":0.0,"TransverseOffset":0.0,"VerticalOffset":0.0,"AxialForce":1.5,"VerticalShear":1.0,"HorizontalShear":10.5,"HorizontalMoment":143.0,"VerticalMoment":16.125,"Torsion":5.9},"ControllingStressTypeResults":{"BracketLegStress":true,"BracketShearRupture":true,"BracketBearing":true,"BracketBolts":true},"GoverningElement":"Bolt &  Bracket","Id":"6929f6ac-6479-4f9a-983e-68e2bdb8a9f7","LoadCase":"","Label":"","RelDist":0.0,"JointLabel":"","LongitudinalOffset":0.0,"TransverseOffset":0.0,"VerticalOffset":0.0,"AxialForce":1.5,"VerticalShear":1.0,"HorizontalShear":10.5,"HorizontalMoment":140.375,"VerticalMoment":15.75,"Torsion":5.9}],"BracketLoadItems":{"Common":[{"LoadsAtPoleFace":{"Id":"6929f6ac-6479-4f9a-983e-68e2bdb8a9f7","LoadCase":"","Label":"","RelDist":0.0,"JointLabel":"","LongitudinalOffset":0.0,"TransverseOffset":0.0,"VerticalOffset":0.0,"AxialForce":1.5,"VerticalShear":1.0,"HorizontalShear":10.5,"HorizontalMoment":143.0,"VerticalMoment":16.125,"Torsion":5.9},"ControllingStressTypeResults":{"BracketLegStress":true,"BracketShearRupture":true,"BracketBearing":true,"BracketBolts":true},"GoverningElement":"Bolt &  Bracket","Id":"6929f6ac-6479-4f9a-983e-68e2bdb8a9f7","LoadCase":"","Label":"","RelDist":0.0,"JointLabel":"","LongitudinalOffset":0.0,"TransverseOffset":0.0,"VerticalOffset":0.0,"AxialForce":1.5,"VerticalShear":1.0,"HorizontalShear":10.5,"HorizontalMoment":140.375,"VerticalMoment":15.75,"Torsion":5.9}]}},"AnalysisWarningMessages":[],"ThruPlateSpec":2,"Azimuth":0.0,"BoltDiameter":1.0,"BoltLength":3.25,"BoltMidSpacing":3.0,"BoltPattern":1,"BoltQty":4,"BoltSideEdgeDistance":1.5,"BoltSpacing":3.0,"BoltSpacingFromFrontPlate":3.0,"BoltSpec":1,"BracketMaterialSpec":2,"BracketThick":0.625,"BracketType":1,"ConnectionType":1,"DesignMethodSpecified":1,"DesignMethodUsed":0,"Finish":1,"Height":18.0,"Id":"00000000-0000-0000-0000-000000000000","Label":null,"MaterialStrength":65.0,"MinimumSideWidth":0.0,"StdBracketID":"Test #1","BracketOpening":15.125,"StiffenerQty":2,"StiffenerThick":0.625,"StiffenerVertSpacing":14.375,"StiffenerWidth":2.5,"ThruPlateThick":0.625,"ThruPlateWidth":0.0},"Label":"","Customer":"","ProjectDescription":"","UseArmPoleOffsets":true,"MyPlateFinish":0}